multicamcomposepro/__init__.py
multicamcomposepro/augment.py
multicamcomposepro/camera.py
multicamcomposepro/main.py
multicamcomposepro/utils.py
mccp-0.2.0.dist-info/LICENSE
mccp-0.2.0.dist-info/METADATA
mccp-0.2.0.dist-info/WHEEL
mccp-0.2.0.dist-info/top_level.txt
mccp-0.2.0.dist-info/RECORD
