Metadata-Version: 2.1
Name: mccp
Version: 0.2.0
Summary: A Python package designed for capturing images from multiple cameras simultaneously. MCCP simplifies the process of data collection for machine learning models and setting up computer vision applications.
Home-page: https://www.github.com/wlinds/mccp
Author: Alexander, William
Author-email: wlinds <w.lindstedt@gmail.com>, Rufshod <alexander@11a.se>
License: MIT license
Project-URL: Homepage, https://github.com/wlinds/mccp
Project-URL: Bug Tracker, https://github.com/wlinds/mccp/issues
Keywords: multicamcomposepro,multicam,compose,pro,multicamcompose,mccp
Classifier: Programming Language :: Python :: 3
Classifier: License :: OSI Approved :: MIT License
Classifier: Operating System :: OS Independent
Requires-Python: >=3.6
License-File: LICENSE
Requires-Dist: opencv-python
Requires-Dist: numpy
Requires-Dist: mkdocstrings[python] >=0.18
Requires-Dist: mkdocs
Requires-Dist: mkdocs-material
Requires-Dist: pytest >=3
